dryads/__init__.py
dryads/checker.py
dryads/common.py
dryads/dryads.py
dryads/exec.py
dryads/helper.py
dryads/shell.py
dryads-2.0.2.dist-info/LICENSE
dryads-2.0.2.dist-info/METADATA
dryads-2.0.2.dist-info/WHEEL
dryads-2.0.2.dist-info/entry_points.txt
dryads-2.0.2.dist-info/RECORD
